MANIFEST.in
README.md
README.txt
ez_setup.py
setup.py
AirbrakePy.egg-info/PKG-INFO
AirbrakePy.egg-info/SOURCES.txt
AirbrakePy.egg-info/dependency_links.txt
AirbrakePy.egg-info/requires.txt
AirbrakePy.egg-info/top_level.txt
AirbrakePy.egg-info/zip-safe
airbrakepy/__init__.py
airbrakepy/metadata.py
airbrakepy/logging/__init__.py
airbrakepy/logging/handlers.py
airbrakepy/test/__init__.py
airbrakepy/test/integration/__init__.py
airbrakepy/test/integration/test-logging.py