Metadata-Version: 1.0
Name: AirbrakePy
Version: 1.0.0b2
Summary: Airbrake notifier for Python logging framework
Home-page: http://github.com/pulseenergy/airbrakepy
Author: Pulse Energy
Author-email: tim at pulseenergy dot com
License: Apache License 2.0
Download-URL: http://github.com/pulseenergy/airbrakepy
Keywords: airbrake python logging
Platform: UNKNOWN
Classifier: Development Status :: 3 - Alpha
Classifier: Topic :: System :: Logging
Classifier: License :: OSI Approved :: Apache Software License
